<?xml version="1.0"?>
<app title="Inventory App">

<model name="item">
    <manufacturer_part_number type="String" length="64" />
    <upc type="String" length="12" />
    <vendor_part_number type="String" length="64" />
    <property_tag type="String" length="64" />
    <location type="String" length="128" />
    <description type="String" length="256" />
    <ip_address type="IP" />
    <mac_address type="EtherMAC" />

    <id>
        <type>Number</type>
        <scale>0</scale>
        <precision>0</precision>
        <primary_key>yes</primary_key>
    </id>
    <entered_by foreign_key_model="user" foreign_key_data="username" />
</model><!--end item-->

<model name="user">
    <fname>
        <type>String</type>
        <length>64</length>
    </fname>

    <lname>
        <type>String</type>
        <length>64</length>
    </lname>

    <username>
        <type>String</type>
        <length>64</length>
        <primary_key>yes</primary_key>
    </username>

    <password>
        <type>Password</type>
        <hash_type>sha1</hash_type>
        <salt>16</salt>
    </password>
</model>

</app>

